sayou/connector/__init__.py
sayou/connector/pipeline.py
sayou/connector/core/exceptions.py
sayou/connector/fetcher/file_fetcher.py
sayou/connector/fetcher/requests_fetcher.py
sayou/connector/fetcher/sqlite_fetcher.py
sayou/connector/generator/file_generator.py
sayou/connector/generator/requests_generator.py
sayou/connector/generator/sqlite_generator.py
sayou/connector/interfaces/base_fetcher.py
sayou/connector/interfaces/base_generator.py
sayou/connector/plugins/github_fetcher.py
sayou/connector/plugins/github_generator.py
sayou/connector/plugins/gmail_fetcher.py
sayou/connector/plugins/gmail_generator.py
sayou/connector/plugins/google_calendar_fetcher.py
sayou/connector/plugins/google_calendar_generator.py
sayou/connector/plugins/google_docs_fetcher.py
sayou/connector/plugins/google_drive_fetcher.py
sayou/connector/plugins/google_drive_generator.py
sayou/connector/plugins/google_sheets_fetcher.py
sayou/connector/plugins/google_slides_fetcher.py
sayou/connector/plugins/google_youtube_fetcher.py
sayou/connector/plugins/google_youtube_generator.py
sayou/connector/plugins/imap_email_fetcher.py
sayou/connector/plugins/imap_email_generator.py
sayou/connector/plugins/mongodb_fetcher.py
sayou/connector/plugins/mongodb_generator.py
sayou/connector/plugins/mssql_fetcher.py
sayou/connector/plugins/mssql_generator.py
sayou/connector/plugins/mysql_fetcher.py
sayou/connector/plugins/mysql_generator.py
sayou/connector/plugins/notion_fetcher.py
sayou/connector/plugins/notion_generator.py
sayou/connector/plugins/obsidian_fetcher.py
sayou/connector/plugins/obsidian_generator.py
sayou/connector/plugins/oracle_fetcher.py
sayou/connector/plugins/oracle_generator.py
sayou/connector/plugins/postgresql_fetcher.py
sayou/connector/plugins/postgresql_generator.py
sayou/connector/plugins/public_youtube_fetcher.py
sayou/connector/plugins/public_youtube_generator.py
sayou/connector/plugins/rss_fetcher.py
sayou/connector/plugins/rss_generator.py
sayou/connector/plugins/trafilatura_fetcher.py
sayou_connector-0.3.24.dist-info/METADATA
sayou_connector-0.3.24.dist-info/WHEEL
sayou_connector-0.3.24.dist-info/RECORD
